rblx_open_cloud-2.3.0.dist-info/licenses/LICENSE
rblxopencloud/__init__.py
rblxopencloud/apikey.py
rblxopencloud/creator.py
rblxopencloud/datastore.py
rblxopencloud/exceptions.py
rblxopencloud/experience.py
rblxopencloud/group.py
rblxopencloud/http.py
rblxopencloud/memorystore.py
rblxopencloud/oauth2.py
rblxopencloud/user.py
rblxopencloud/webhook.py
rblxopencloudasync/__init__.py
rblxopencloudasync/apikey.py
rblxopencloudasync/creator.py
rblxopencloudasync/datastore.py
rblxopencloudasync/exceptions.py
rblxopencloudasync/experience.py
rblxopencloudasync/group.py
rblxopencloudasync/http.py
rblxopencloudasync/memorystore.py
rblxopencloudasync/oauth2.py
rblxopencloudasync/user.py
rblxopencloudasync/webhook.py
rblx_open_cloud-2.3.0.dist-info/METADATA
rblx_open_cloud-2.3.0.dist-info/WHEEL
rblx_open_cloud-2.3.0.dist-info/top_level.txt
rblx_open_cloud-2.3.0.dist-info/RECORD
