Metadata-Version: 2.4
Name: rblx-open-cloud
Version: 2.3.0
Summary: API wrapper for Roblox Open Cloud
Home-page: https://github.com/treeben77/rblx-open-cloud
Author: treeben77
License: MIT
Keywords: roblox,open-cloud,data-store,place-publishing,mesageing-service
Requires-Python: >=3.9.0
License-File: LICENSE
Requires-Dist: requests
Requires-Dist: aiohttp
Requires-Dist: cryptography
Requires-Dist: pyjwt
Requires-Dist: python-dateutil
Requires-Dist: PyNaCl
Dynamic: author
Dynamic: description
Dynamic: description-content-type
Dynamic: home-page
Dynamic: keywords
Dynamic: license
Dynamic: license-file
Dynamic: requires-dist
Dynamic: requires-python
Dynamic: summary
